{
  "id": 1,
  "title": "바디 & 핸드",
  "link": "/",
  "subCategories": [
    {
      "id": 1,
      "title": "핸드",
      "desc": "매일 우리에게 안락함을 선사하는 손은 보살핌을 받을 자격이 충분합니다. 아로마 클렌저와 밤은 손에 수분과 영양을 공급하고 부드럽게 가꿔줍니다.",
      "link": "/",
      "list": [
        {
          "id": 1,
          "title": "에이 로즈 바이 애니 아더 네임 바디 클렌저",
          "size": [150],
          "price": 10000,
          "imgSrc": "/images/1.png"
        },
        {
          "id": 2,
          "title": "에이 로즈 바이 애니 아더 네임 바디 클렌저",
          "size": [150, 300],
          "price": 100000,
          "imgSrc": "/images/2.png"
        },
        {
          "id": 3,
          "title": "에이 로즈 바이 애니 아더 네임 바디 클렌저",
          "size": [150, 300, 450],
          "price": 1000000,
          "imgSrc": "/images/3.png"
        },
        {
          "id": 4,
          "title": "에이 로즈 바이 애니 아더 네임 바디 클렌저",
          "size": [150, 300, 450, 600],
          "price": 10000000,
          "imgSrc": "/images/4.png"
        },
        {
          "id": 5,
          "title": "에이 로즈 바이 애니 아더 네임 바디 클렌저",
          "size": [150, 300, 450, 600, 750],
          "price": 100000000,
          "imgSrc": "/images/5.png"
        }
      ]
    },
    {
      "id": 2,
      "title": "바디",
      "desc": "보태니컬 원료가 풍부하게 함유된 바디 클렌저, 하이드레이터 그리고 부드러운 바디 트리트먼트 오일은 깨끗하고 부드러운 피부를 오랫동안 유지하도록 도와줍니다.",
      "link": "/",
      "list": [
        {
          "id": 1,
          "title": "에이 로즈 바이 애니 아더 네임 바디 클렌저",
          "size": [150],
          "price": 10000,
          "imgSrc": "/images/1.png"
        },
        {
          "id": 2,
          "title": "에이 로즈 바이 애니 아더 네임 바디 클렌저",
          "size": [150, 300],
          "price": 100000,
          "imgSrc": "/images/2.png"
        },
        {
          "id": 3,
          "title": "에이 로즈 바이 애니 아더 네임 바디 클렌저",
          "size": [150, 300, 450],
          "price": 1000000,
          "imgSrc": "/images/3.png"
        },
        {
          "id": 4,
          "title": "에이 로즈 바이 애니 아더 네임 바디 클렌저",
          "size": [150, 300, 450, 600],
          "price": 10000000,
          "imgSrc": "/images/4.png"
        },
        {
          "id": 5,
          "title": "에이 로즈 바이 애니 아더 네임 바디 클렌저",
          "size": [150, 300, 450, 600, 750],
          "price": 100000000,
          "imgSrc": "/images/5.png"
        }
      ]
    },
    {
      "id": 3,
      "title": "퍼스널 케어",
      "desc": "어디서든 손쉽게 사용할 수 있는 퍼스널 케어 제품은 매일 사용하는 이솝의 스킨, 바디 케어와 잘 어울립니다.",
      "link": "/",
      "list": [
        {
          "id": 1,
          "title": "에이 로즈 바이 애니 아더 네임 바디 클렌저",
          "size": [150],
          "price": 10000,
          "imgSrc": "/images/1.png"
        },
        {
          "id": 2,
          "title": "에이 로즈 바이 애니 아더 네임 바디 클렌저",
          "size": [150, 300],
          "price": 100000,
          "imgSrc": "/images/2.png"
        },
        {
          "id": 3,
          "title": "에이 로즈 바이 애니 아더 네임 바디 클렌저",
          "size": [150, 300, 450],
          "price": 1000000,
          "imgSrc": "/images/3.png"
        },
        {
          "id": 4,
          "title": "에이 로즈 바이 애니 아더 네임 바디 클렌저",
          "size": [150, 300, 450, 600],
          "price": 10000000,
          "imgSrc": "/images/4.png"
        },
        {
          "id": 5,
          "title": "에이 로즈 바이 애니 아더 네임 바디 클렌저",
          "size": [150, 300, 450, 600, 750],
          "price": 100000000,
          "imgSrc": "/images/5.png"
        }
      ]
    },
    {
      "id": 4,
      "title": "핸드 및 바디 케어 기프트",
      "desc": "일상적인 의식에 기쁨을 선사하는 비누, 젤 클렌저, 밤, 오일, 스크럽 등 다양한 바디 제품은 향기롭고 효능이 뛰어난 기프트를 구성해 받는 분들에게 즐거움을 선사합니다.",
      "link": "/",
      "list": [
        {
          "id": 1,
          "title": "에이 로즈 바이 애니 아더 네임 바디 클렌저",
          "size": [150],
          "price": 10000,
          "imgSrc": "/images/1.png"
        },
        {
          "id": 2,
          "title": "에이 로즈 바이 애니 아더 네임 바디 클렌저",
          "size": [150, 300],
          "price": 100000,
          "imgSrc": "/images/2.png"
        },
        {
          "id": 3,
          "title": "에이 로즈 바이 애니 아더 네임 바디 클렌저",
          "size": [150, 300, 450],
          "price": 1000000,
          "imgSrc": "/images/3.png"
        },
        {
          "id": 4,
          "title": "에이 로즈 바이 애니 아더 네임 바디 클렌저",
          "size": [150, 300, 450, 600],
          "price": 10000000,
          "imgSrc": "/images/4.png"
        },
        {
          "id": 5,
          "title": "에이 로즈 바이 애니 아더 네임 바디 클렌저",
          "size": [150, 300, 450, 600, 750],
          "price": 100000000,
          "imgSrc": "/images/5.png"
        }
      ]
    }
  ]
}
